sysframe/__init__.py
sysframe/membridge/__init__.py
sysframe/membridge/membridge.c
sysframe/membridge/membridge.pyi
sysframe/membridge/membridge.pypy37-pp73-x86-linux-gnu.so
sysframe/pybytes/__init__.py
sysframe/pybytes/pybytes.pyi
sysframe/pybytes/pybytes.c
sysframe/pybytes/pybytes.pypy37-pp73-x86-linux-gnu.so
sysframe/pybytes/sbs_old/sbs_1.c
sysframe/pybytes/sbs_main/sbs_2.c
sysframe-0.4.1.dist-info/METADATA
sysframe-0.4.1.dist-info/LICENSE
sysframe-0.4.1.dist-info/top_level.txt
sysframe-0.4.1.dist-info/WHEEL
sysframe-0.4.1.dist-info/RECORD
