Metadata-Version: 2.1
Name: sysframe
Version: 0.4.1
Summary: A collection of modules useful for low-level development tasks.
Home-page: https://github.com/svenboertjens/sysframe
Author: Sven Boertjens
Author-email: boertjens.sven@gmail.com
License: UNKNOWN
Platform: UNKNOWN
Classifier: Programming Language :: Python :: 3
Classifier: License :: OSI Approved :: MIT License
Classifier: Operating System :: POSIX :: Linux
Requires-Python: >=3.6, <3.13
License-File: LICENSE
